process_managerial/QueueSystem.py
process_managerial/__init__.py
process_managerial/toolbox.py
process_managerial-0.1.22.dist-info/licenses/LICENSE
process_managerial-0.1.22.dist-info/METADATA
process_managerial-0.1.22.dist-info/WHEEL
process_managerial-0.1.22.dist-info/top_level.txt
process_managerial-0.1.22.dist-info/RECORD
