Metadata-Version: 2.4
Name: process_managerial
Version: 0.1.22
Summary: Connor's Process Managerial (PM) is a utility that processes and enques functions.
Author-email: Connor White <connor.sw.personal@gmail.com>
License-Expression: MIT
Project-URL: Homepage, https://github.com/CorniiDog/process_managerial
Project-URL: Issues, https://github.com/CorniiDog/process_managerial/issues
Classifier: Programming Language :: Python :: 3
Classifier: Operating System :: OS Independent
Requires-Python: >=3.9
License-File: LICENSE
Dynamic: license-file
